openai_functions/__init__.py
openai_functions/conversation.py
openai_functions/exceptions.py
openai_functions/functions/__init__.py
openai_functions/functions/basic_set.py
openai_functions/functions/functions.py
openai_functions/functions/sets.py
openai_functions/functions/togglable_set.py
openai_functions/functions/union.py
openai_functions/functions/wrapper.py
openai_functions/json_type.py
openai_functions/nlp.py
openai_functions/openai_types.py
openai_functions/parsers/__init__.py
openai_functions/parsers/abc.py
openai_functions/parsers/atomic_type_parser.py
openai_functions/parsers/bool_parser.py
openai_functions/parsers/dataclass_parser.py
openai_functions/parsers/default.py
openai_functions/parsers/dict_parser.py
openai_functions/parsers/enum_parser.py
openai_functions/parsers/float_parser.py
openai_functions/parsers/int_parser.py
openai_functions/parsers/list_parser.py
openai_functions/parsers/none_parser.py
openai_functions/parsers/str_parser.py
openai_functions/parsers/union_parser.py
openai_functions/py.typed
openai_functions-1.0.2.dist-info/LICENSE
openai_functions-1.0.2.dist-info/METADATA
openai_functions-1.0.2.dist-info/WHEEL
openai_functions-1.0.2.dist-info/RECORD
