Metadata-Version: 2.1
Name: openai-functions
Version: 1.0.2
Summary: Simplifies the usage of OpenAI ChatGPT's function calling by generating the schemas and parsing OpenAI's responses for you.
Home-page: https://github.com/rizerphe/openai-functions
License: MIT
Keywords: nlp,openai,openai-api,chatgpt,chatgpt-api,wrapper,functions,chatgpt-api,openai-functions,chatgpt-functions,typing,docstring,docstrings,decorators,signatures,parsing
Author: rizerphe
Author-email: 44440399+rizerphe@users.noreply.github.com
Requires-Python: >=3.8,<4.0
Classifier: License :: OSI Approved :: MIT License
Classifier: Programming Language :: Python :: 3
Classifier: Programming Language :: Python :: 3.8
Classifier: Programming Language :: Python :: 3.9
Classifier: Programming Language :: Python :: 3.10
Classifier: Programming Language :: Python :: 3.11
Requires-Dist: docstring-parser (>=0.15,<0.16)
Requires-Dist: openai (>=0.27.8,<0.28.0)
Requires-Dist: typing-extensions (>=4.6.3,<5.0.0)
Project-URL: Documentation, https://openai-functions.readthedocs.io/
